[
 {
  "content": "<div><img src=\"/files/VXcTglx.png\"></div>", 
  "disabled": 0, 
  "docstatus": 0, 
  "doctype": "Letter Head", 
  "footer": null, 
  "is_default": 1, 
  "letter_head_name": "Letterhead Official", 
  "modified": "2019-01-02 21:01:44.151687", 
  "name": "Letterhead Official"
 }, 
 {
  "content": "<div><img src=\"/files/630Q8O5.png\"></div>", 
  "disabled": 0, 
  "docstatus": 0, 
  "doctype": "Letter Head", 
  "footer": null, 
  "is_default": 0, 
  "letter_head_name": "Letterhead Internal", 
  "modified": "2019-01-02 21:00:51.525128", 
  "name": "Letterhead Internal"
 }
]